Workbook

Sheet Read Me
B2: Paper-Trading Tracker | started 8 Oct 2026
B3: Mock-invest the plan until the real start in January 2027. All figures are hypothetical.
B5: HOW TO USE
B6: 1. Weekly Log sheet: enter the baseline prices in the yellow cells of row 2 (what each fund cost on 8 Oct 2026, from the Sarwa app or a quote source). Each week, add a new row with the date and closing prices.
B7: 2. Ledger sheet: the first four mock buys (8 Oct 2026) are pre-loaded. Enter your fill price in the yellow cells. Fill prices are what you would have paid, not today's price on a later day.
B8: 3. Each payday (1st of the month): add four new rows to the Ledger and one row to the Contributions sheet. Current prices on Setup update automatically from the latest Weekly Log row.
B9: 4. Weekly Dashboard sheet: the weekly review view (core, ballast, satellite, trend, news). Dashboard sheet: detailed positions, drift and the payday buy planner.
B11: COLOUR LEGEND
B12: Blue text = an input you or the plan set. Yellow fill = a cell you must fill in. Black text = formula, do not overwrite. Weekly Log rows must be contiguous (no gaps).
B14: EXAMPLE ENTRY (format only)
B15: Weekly Log row: Date 2026-10-15 | VOO 150.00 | SGOV 100.60 | ITA 158.00 | NLR 98.00 | CEG 270.00 | CCJ 85.00 (format only; not real prices).
B17: ASSUMPTIONS (change them on the Setup sheet)
... B28: This workbook is a stopgap. The Vercel dashboard from the brief will automate prices and add return and drawdown analytics.

Sheet Weekly Dashboard
A1: Weekly Dashboard
A2: ="Latest weekly entry: "&IF(COUNT('Weekly Log'!$A$2:$A$60)=0,"none yet",TEXT(INDEX('Weekly Log'!$A$2:$A$60,COUNT('Weekly Log'!$A$2:$A$60)),"d mmm yyyy"))&" | Hypothetical paper portfolio" -> Latest weekly entry: 8 Oct 2026 | Hypothetical paper portfolio
A4: Company | B4: Code | C4: This week % | D4: $ invested to date | E4: Since first investment % (price) | F4: Overall P/L % | G4: Overall P/L $ | H4: Trend (last 4 weeks)
A5: ="CORE | target "&TEXT(Setup!C9,"0.0#%") -> CORE | target 65.0%
A6: Vanguard S&P 500 ETF | B6: VOO | C6: =IF(COUNT('Weekly Log'!B$2:B$60)<2,"",IFERROR(INDEX('Weekly Log'!B$2:B$60,COUNT('Weekly Log'!B$2:B$60))/INDEX('Weekly Log'!B$2:B$60,COUNT('Weekly Log'!B$2:B$60)-1)-1,"")) | D6: =Dashboard!E5 -> 707.9646 | E6: =IF(COUNT('Weekly Log'!B$2:B$60)<2,"",IFERROR(INDEX('Weekly Log'!B$2:B$60,COUNT('Weekly Log'!B$2:B$60))/INDEX('Weekly Log'!B$2:B$60,1)-1,"")) | F6: =Dashboard!J5 | G6: =Dashboard!I5 | H6: =IF(COUNT('Weekly Log'!B$2:B$60)<2,"",IF(COUNT('Weekly Log'!B$2:B$60)>=4,IF(INDEX('Weekly Log'!B$2:B$60,COUNT('Weekly Log'!B$2:B$60)-2)>INDEX('Weekly Log'!B$2:B$60,COUNT('Weekly Log'!B$2:B$60)-3),"▲",IF(INDEX('Weekly Log'!B$2:B$60,COUNT('Weekly Log'!B$2:B$60)-2)<INDEX('Weekly Log'!B$2:B$60,COUNT('Weekly Log'!B$2:B$60)-3),"▼","▬"))&" ","")&IF(COUNT('Weekly Log'!B$2:B$60)>=3,IF(INDEX('Weekly Log'!B$2:B$60,COUNT('Weekly Log'!B$2:B$60)-1)>INDEX('Weekly Log'!B$2:B$60,COUNT('Weekly Log'!B$2:B$60)-2),"▲",IF(INDEX('Weekly Log'!B$2:B$60,COUNT('Weekly Log'!B$2:B$60)-1)<INDEX('Weekly Log'!B$2:B$60,COUNT('Weekly Log'!B$2:B$60)-2),"▼","▬"))&" ","")&IF(INDEX('Weekly Log'!B$2:B$60,COUNT('Weekly Log'!B$2:B$60))>INDEX('Weekly Log'!B$2:B$60,COUNT('Weekly Log'!B$2:B$60)-1),"▲",IF(INDEX('Weekly Log'!B$2:B$60,COUNT('Weekly Log'!B$2:B$60))<INDEX('Weekly Log'!B$2:B$60,COUNT('Weekly Log'!B$2:B$60)-1),"▼","▬")))
A7: ="BALLAST | target "&TEXT(Setup!C10,"0.0#%") -> BALLAST | target 12.5%
A8: iShares 0-3 Month Treasury Bond ETF | B8: SGOV | C8: =IF(COUNT('Weekly Log'!C$2:C$60)<2,"",IFERROR(INDEX('Weekly Log'!C$2:C$60,COUNT('Weekly Log'!C$2:C$60))/INDEX('Weekly Log'!C$2:C$60,COUNT('Weekly Log'!C$2:C$60)-1)-1,"")) | D8: =Dashboard!E6 -> 136.14704 | E8: =IF(COUNT('Weekly Log'!C$2:C$60)<2,"",IFERROR(INDEX('Weekly Log'!C$2:C$60,COUNT('Weekly Log'!C$2:C$60))/INDEX('Weekly Log'!C$2:C$60,1)-1,"")) | F8: =Dashboard!J6 | G8: =Dashboard!I6 | H8: =IF(COUNT('Weekly Log'!C$2:C$60)<2,"",IF(COUNT('Weekly Log'!C$2:C$60)>=4,IF(INDEX('Weekly Log'!C$2:C$60,COUNT('Weekly Log'!C$2:C$60)-2)>INDEX('Weekly Log'!C$2:C$60,COUNT('Weekly Log'!C$2:C$60)-3),"▲",IF(INDEX('Weekly Log'!C$2:C$60,COUNT('Weekly Log'!C$2:C$60)-2)<INDEX('Weekly Log'!C$2:C$60,COUNT('Weekly Log'!C$2:C$60)-3),"▼","▬"))&" ","")&IF(COUNT('Weekly Log'!C$2:C$60)>=3,IF(INDEX('Weekly Log'!C$2:C$60,COUNT('Weekly Log'!C$2:C$60)-1)>INDEX('Weekly Log'!C$2:C$60,COUNT('Weekly Log'!C$2:C$60)-2),"▲",IF(INDEX('Weekly Log'!C$2:C$60,COUNT('Weekly Log'!C$2:C$60)-1)<INDEX('Weekly Log'!C$2:C$60,COUNT('Weekly Log'!C$2:C$60)-2),"▼","▬"))&" ","")&IF(INDEX('Weekly Log'!C$2:C$60,COUNT('Weekly Log'!C$2:C$60))>INDEX('Weekly Log'!C$2:C$60,COUNT('Weekly Log'!C$2:C$60)-1),"▲",IF(INDEX('Weekly Log'!C$2:C$60,COUNT('Weekly Log'!C$2:C$60))<INDEX('Weekly Log'!C$2:C$60,COUNT('Weekly Log'!C$2:C$60)-1),"▼","▬")))
A9: ="SATELLITE | target "&TEXT(Setup!C11+Setup!C12,"0.0#%") -> SATELLITE | target 22.5%
A10: iShares U.S. Aerospace & Defense ETF | B10: ITA | C10: =IF(COUNT('Weekly Log'!D$2:D$60)<2,"",IFERROR(INDEX('Weekly Log'!D$2:D$60,COUNT('Weekly Log'!D$2:D$60))/INDEX('Weekly Log'!D$2:D$60,COUNT('Weekly Log'!D$2:D$60)-1)-1,"")) | D10: =Dashboard!E7 -> 122.53233 | E10: =IF(COUNT('Weekly Log'!D$2:D$60)<2,"",IFERROR(INDEX('Weekly Log'!D$2:D$60,COUNT('Weekly Log'!D$2:D$60))/INDEX('Weekly Log'!D$2:D$60,1)-1,"")) | F10: =Dashboard!J7 | G10: =Dashboard!I7 | H10: =IF(COUNT('Weekly Log'!D$2:D$60)<2,"",IF(COUNT('Weekly Log'!D$2:D$60)>=4,IF(INDEX('Weekly Log'!D$2:D$60,COUNT('Weekly Log'!D$2:D$60)-2)>INDEX('Weekly Log'!D$2:D$60,COUNT('Weekly Log'!D$2:D$60)-3),"▲",IF(INDEX('Weekly Log'!D$2:D$60,COUNT('Weekly Log'!D$2:D$60)-2)<INDEX('Weekly Log'!D$2:D$60,COUNT('Weekly Log'!D$2:D$60)-3),"▼","▬"))&" ","")&IF(COUNT('Weekly Log'!D$2:D$60)>=3,IF(INDEX('Weekly Log'!D$2:D$60,COUNT('Weekly Log'!D$2:D$60)-1)>INDEX('Weekly Log'!D$2:D$60,COUNT('Weekly Log'!D$2:D$60)-2),"▲",IF(INDEX('Weekly Log'!D$2:D$60,COUNT('Weekly Log'!D$2:D$60)-1)<INDEX('Weekly Log'!D$2:D$60,COUNT('Weekly Log'!D$2:D$60)-2),"▼","▬"))&" ","")&IF(INDEX('Weekly Log'!D$2:D$60,COUNT('Weekly Log'!D$2:D$60))>INDEX('Weekly Log'!D$2:D$60,COUNT('Weekly Log'!D$2:D$60)-1),"▲",IF(INDEX('Weekly Log'!D$2:D$60,COUNT('Weekly Log'!D$2:D$60))<INDEX('Weekly Log'!D$2:D$60,COUNT('Weekly Log'!D$2:D$60)-1),"▼","▬")))
A11: VanEck Uranium and Nuclear ETF | B11: NLR | C11: =IF(COUNT('Weekly Log'!E$2:E$60)<2,"",IFERROR(INDEX('Weekly Log'!E$2:E$60,COUNT('Weekly Log'!E$2:E$60))/INDEX('Weekly Log'!E$2:E$60,COUNT('Weekly Log'!E$2:E$60)-1)-1,"")) | D11: =Dashboard!E8 -> 122.53233 | E11: =IF(COUNT('Weekly Log'!E$2:E$60)<2,"",IFERROR(INDEX('Weekly Log'!E$2:E$60,COUNT('Weekly Log'!E$2:E$60))/INDEX('Weekly Log'!E$2:E$60,1)-1,"")) | F11: =Dashboard!J8 | G11: =Dashboard!I8 | H11: =IF(COUNT('Weekly Log'!E$2:E$60)<2,"",IF(COUNT('Weekly Log'!E$2:E$60)>=4,IF(INDEX('Weekly Log'!E$2:E$60,COUNT('Weekly Log'!E$2:E$60)-2)>INDEX('Weekly Log'!E$2:E$60,COUNT('Weekly Log'!E$2:E$60)-3),"▲",IF(INDEX('Weekly Log'!E$2:E$60,COUNT('Weekly Log'!E$2:E$60)-2)<INDEX('Weekly Log'!E$2:E$60,COUNT('Weekly Log'!E$2:E$60)-3),"▼","▬"))&" ","")&IF(COUNT('Weekly Log'!E$2:E$60)>=3,IF(INDEX('Weekly Log'!E$2:E$60,COUNT('Weekly Log'!E$2:E$60)-1)>INDEX('Weekly Log'!E$2:E$60,COUNT('Weekly Log'!E$2:E$60)-2),"▲",IF(INDEX('Weekly Log'!E$2:E$60,COUNT('Weekly Log'!E$2:E$60)-1)<INDEX('Weekly Log'!E$2:E$60,COUNT('Weekly Log'!E$2:E$60)-2),"▼","▬"))&" ","")&IF(INDEX('Weekly Log'!E$2:E$60,COUNT('Weekly Log'!E$2:E$60))>INDEX('Weekly Log'!E$2:E$60,COUNT('Weekly Log'!E$2:E$60)-1),"▲",IF(INDEX('Weekly Log'!E$2:E$60,COUNT('Weekly Log'!E$2:E$60))<INDEX('Weekly Log'!E$2:E$60,COUNT('Weekly Log'!E$2:E$60)-1),"▼","▬")))
A12: COMPARISONS | paper only, no money assigned (learning experiment)
A13: Constellation Energy (an NLR top holding) | B13: CEG | C13: =IF(COUNT('Weekly Log'!F$2:F$60)<2,"",IFERROR(INDEX('Weekly Log'!F$2:F$60,COUNT('Weekly Log'!F$2:F$60))/INDEX('Weekly Log'!F$2:F$60,COUNT('Weekly Log'!F$2:F$60)-1)-1,"")) | D13: n/a | E13: =IF(COUNT('Weekly Log'!F$2:F$60)<2,"",IFERROR(INDEX('Weekly Log'!F$2:F$60,COUNT('Weekly Log'!F$2:F$60))/INDEX('Weekly Log'!F$2:F$60,1)-1,"")) | F13: n/a | G13: n/a | H13: =IF(COUNT('Weekly Log'!F$2:F$60)<2,"",IF(COUNT('Weekly Log'!F$2:F$60)>=4,IF(INDEX('Weekly Log'!F$2:F$60,COUNT('Weekly Log'!F$2:F$60)-2)>INDEX('Weekly Log'!F$2:F$60,COUNT('Weekly Log'!F$2:F$60)-3),"▲",IF(INDEX('Weekly Log'!F$2:F$60,COUNT('Weekly Log'!F$2:F$60)-2)<INDEX('Weekly Log'!F$2:F$60,COUNT('Weekly Log'!F$2:F$60)-3),"▼","▬"))&" ","")&IF(COUNT('Weekly Log'!F$2:F$60)>=3,IF(INDEX('Weekly Log'!F$2:F$60,COUNT('Weekly Log'!F$2:F$60)-1)>INDEX('Weekly Log'!F$2:F$60,COUNT('Weekly Log'!F$2:F$60)-2),"▲",IF(INDEX('Weekly Log'!F$2:F$60,COUNT('Weekly Log'!F$2:F$60)-1)<INDEX('Weekly Log'!F$2:F$60,COUNT('Weekly Log'!F$2:F$60)-2),"▼","▬"))&" ","")&IF(INDEX('Weekly Log'!F$2:F$60,COUNT('Weekly Log'!F$2:F$60))>INDEX('Weekly Log'!F$2:F$60,COUNT('Weekly Log'!F$2:F$60)-1),"▲",IF(INDEX('Weekly Log'!F$2:F$60,COUNT('Weekly Log'!F$2:F$60))<INDEX('Weekly Log'!F$2:F$60,COUNT('Weekly Log'!F$2:F$60)-1),"▼","▬")))
A14: Cameco (an NLR top holding) | B14: CCJ | C14: =IF(COUNT('Weekly Log'!G$2:G$60)<2,"",IFERROR(INDEX('Weekly Log'!G$2:G$60,COUNT('Weekly Log'!G$2:G$60))/INDEX('Weekly Log'!G$2:G$60,COUNT('Weekly Log'!G$2:G$60)-1)-1,"")) | D14: n/a | E14: =IF(COUNT('Weekly Log'!G$2:G$60)<2,"",IFERROR(INDEX('Weekly Log'!G$2:G$60,COUNT('Weekly Log'!G$2:G$60))/INDEX('Weekly Log'!G$2:G$60,1)-1,"")) | F14: n/a | G14: n/a | H14: =IF(COUNT('Weekly Log'!G$2:G$60)<2,"",IF(COUNT('Weekly Log'!G$2:G$60)>=4,IF(INDEX('Weekly Log'!G$2:G$60,COUNT('Weekly Log'!G$2:G$60)-2)>INDEX('Weekly Log'!G$2:G$60,COUNT('Weekly Log'!G$2:G$60)-3),"▲",IF(INDEX('Weekly Log'!G$2:G$60,COUNT('Weekly Log'!G$2:G$60)-2)<INDEX('Weekly Log'!G$2:G$60,COUNT('Weekly Log'!G$2:G$60)-3),"▼","▬"))&" ","")&IF(COUNT('Weekly Log'!G$2:G$60)>=3,IF(INDEX('Weekly Log'!G$2:G$60,COUNT('Weekly Log'!G$2:G$60)-1)>INDEX('Weekly Log'!G$2:G$60,COUNT('Weekly Log'!G$2:G$60)-2),"▲",IF(INDEX('Weekly Log'!G$2:G$60,COUNT('Weekly Log'!G$2:G$60)-1)<INDEX('Weekly Log'!G$2:G$60,COUNT('Weekly Log'!G$2:G$60)-2),"▼","▬"))&" ","")&IF(INDEX('Weekly Log'!G$2:G$60,COUNT('Weekly Log'!G$2:G$60))>INDEX('Weekly Log'!G$2:G$60,COUNT('Weekly Log'!G$2:G$60)-1),"▲",IF(INDEX('Weekly Log'!G$2:G$60,COUNT('Weekly Log'!G$2:G$60))<INDEX('Weekly Log'!G$2:G$60,COUNT('Weekly Log'!G$2:G$60)-1),"▼","▬")))
A16: TOTAL PORTFOLIO | D16: =Dashboard!E9 -> 1089.1763 | F16: =Dashboard!J9 | G16: =Dashboard!I9
A17: Benchmark: same contributions, 100% VOO | F17: =Dashboard!E19
A18: Portfolio minus benchmark (points) | F18: =Dashboard!E20
A19: Overall P/L % uses your cost basis including fees. 'Since first investment %' is price change only, from the baseline row in the Weekly Log.
A21: THIS WEEK'S NEWS | as of 8 Oct 2026 | rewrite each week
A22: Holding | B22: Code | C22: What is happening, and why it may matter
A23: S&P 500 (core) | B23: VOO | C23: S&P 500 closed 7,722.72 on 2 Oct, about 1% below its August record; Nasdaq up about 17% for the year. The pressure point is the US 10-year yield near 5.28%, the highest since 2007. Breadth is weak and the AI buildout is propping up the index. VOO is 100% US large caps with roughly 38% in its top ten holdings, so it moves directly with this. Q3 earnings season starts around 12 Oct.
A24: Short-term Treasuries (ballast) | B24: SGOV | C24: The Fed returned to rate hikes in September, so T-bill yields are high: good income, very little price risk. A shift toward cuts would lower the income, not the price. No fund-specific news.
A25: US aerospace and defense (satellite) | B25: ITA | C25: The administration is asking Congress for a $1.5 trillion FY2027 defense budget (about 50%+ above current), including $20 billion for Golden Dome and $65 billion for a Navy shipbuilding plan. Lawmakers from both parties are questioning the size and the legal basis for Iran operations; the ceasefire is described as fragile and the conflict's cost estimate rose from $25 billion to $29 billion. Budget approval is not guaranteed, and a durable peace could shrink the fear premium.
A26: Uranium and nuclear (satellite) | B26: NLR | C26: Uranium hit a 19-year price record (above $96/lb) yet nuclear stocks keep falling: NLR is down about 16% year-to-date, Uranium Energy about 20%. Reporting points to utilities not yet signing contracts at the higher price, possible US tariffs on uranium, a longer Q3 shutdown at Cameco's Key Lake mill, weak sentiment toward commodity stocks, and investors demanding proof after the AI-nuclear hype.
A27: Constellation Energy (comparison) | B27: CEG | C27: No verified news for this week. Background: 2026 adjusted operating earnings guidance of $11 to $12 per share, over 5,650 MW of long-term clean-energy agreements including data-centre deals, investment-grade rating after the Calpine acquisition. Stock has been volatile. Check the next quarterly update.
A28: Cameco (comparison) | B28: CCJ | C28: Closed $85.18 on 2 Oct: down about 7% for 2026 and 11.6% over the past month. Valuation is stretched (trailing P/E about 149, forward about 52). Flagged risks: possible US uranium tariffs and the extended Key Lake shutdown. Next earnings reported for 30 Oct.
A30: Sources for this week's news: market wrap and uranium reports dated 2-3 Oct 2026, Pentagon budget hearing coverage, company guidance releases. Verify before acting.

Sheet Dashboard
A1: Paper Portfolio Dashboard
A2: Hypothetical. Gain/loss appears once fill prices and current prices are entered.
A4: Ticker | B4: Sleeve | C4: Target | D4: AED invested | E4: USD invested (incl. fees) | F4: Units | G4: Current price | H4: Market value (USD) | I4: Gain/loss (USD) | J4: Gain/loss % | K4: Weight | L4: Drift vs target
A5: =Setup!B9 -> VOO | B5: =Setup!A9 -> US equity (S&P 500) | C5: =Setup!C9 -> 0.65 | D5: =SUMIFS(Ledger!$D$2:$D$200,Ledger!$B$2:$B$200,A5) -> 2600 | E5: =SUMIFS(Ledger!$E$2:$E$200,Ledger!$B$2:$B$200,A5) -> 707.9646 | F5: =SUMIFS(Ledger!$H$2:$H$200,Ledger!$B$2:$B$200,A5) -> 0 | G5: =IF(Setup!D9="","",Setup!D9) | H5: =IF(OR(G5="",F5=0),"",F5*G5) | I5: =IF(H5="","",H5-E5) | J5: =IF(OR(H5="",E5=0),"",I5/E5) | K5: =IF(OR(H5="",$H$9=""),"",H5/$H$9) | L5: =IF(K5="","",K5-C5)
A6: =Setup!B10 -> SGOV | B6: =Setup!A10 -> Short-term Treasuries / TIPS | C6: =Setup!C10 -> 0.125 | D6: =SUMIFS(Ledger!$D$2:$D$200,Ledger!$B$2:$B$200,A6) -> 500 | E6: =SUMIFS(Ledger!$E$2:$E$200,Ledger!$B$2:$B$200,A6) -> 136.14704 | F6: =SUMIFS(Ledger!$H$2:$H$200,Ledger!$B$2:$B$200,A6) -> 0 | G6: =IF(Setup!D10="","",Setup!D10) | H6: =IF(OR(G6="",F6=0),"",F6*G6) | I6: =IF(H6="","",H6-E6) | J6: =IF(OR(H6="",E6=0),"",I6/E6) | K6: =IF(OR(H6="",$H$9=""),"",H6/$H$9) | L6: =IF(K6="","",K6-C6)
A7: =Setup!B11 -> ITA | B7: =Setup!A11 -> Defense / aerospace | C7: =Setup!C11 -> 0.1125 | D7: =SUMIFS(Ledger!$D$2:$D$200,Ledger!$B$2:$B$200,A7) -> 450 | E7: =SUMIFS(Ledger!$E$2:$E$200,Ledger!$B$2:$B$200,A7) -> 122.53233 | F7: =SUMIFS(Ledger!$H$2:$H$200,Ledger!$B$2:$B$200,A7) -> 0 | G7: =IF(Setup!D11="","",Setup!D11) | H7: =IF(OR(G7="",F7=0),"",F7*G7) | I7: =IF(H7="","",H7-E7) | J7: =IF(OR(H7="",E7=0),"",I7/E7) | K7: =IF(OR(H7="",$H$9=""),"",H7/$H$9) | L7: =IF(K7="","",K7-C7)
A8: =Setup!B12 -> NLR | B8: =Setup!A12 -> Nuclear energy | C8: =Setup!C12 -> 0.1125 | D8: =SUMIFS(Ledger!$D$2:$D$200,Ledger!$B$2:$B$200,A8) -> 450 | E8: =SUMIFS(Ledger!$E$2:$E$200,Ledger!$B$2:$B$200,A8) -> 122.53233 | F8: =SUMIFS(Ledger!$H$2:$H$200,Ledger!$B$2:$B$200,A8) -> 0 | G8: =IF(Setup!D12="","",Setup!D12) | H8: =IF(OR(G8="",F8=0),"",F8*G8) | I8: =IF(H8="","",H8-E8) | J8: =IF(OR(H8="",E8=0),"",I8/E8) | K8: =IF(OR(H8="",$H$9=""),"",H8/$H$9) | L8: =IF(K8="","",K8-C8)
A9: Total | C9: =SUM(C5:C8) -> 1 | D9: =SUM(D5:D8) -> 4000 | E9: =SUM(E5:E8) -> 1089.1763 | H9: =IF(COUNT(H5:H8)=4,SUM(H5:H8),"") | I9: =IF(H9="","",H9-E9) | J9: =IF(OR(H9="",E9=0),"",I9/E9)
A11: Total gain/loss (AED) | E11: =IF(I9="","",I9*Setup!B3)
A12: Fees paid to date (USD) | E12: =SUM(Ledger!F2:F200) -> 4.7699115
A13: Fee drag (% of USD invested) | E13: =IF(E9=0,"",E12/E9) -> 0.004379375
A15: Benchmark: same contributions, 100% VOO
A16: USD invested (incl. fees) | E16: =SUM(Contributions!D2:D61) -> 1089.1763
A17: Units of VOO | E17: =SUM(Contributions!F2:F61) -> 0
A18: Market value (USD) | E18: =IF(OR(Setup!D9="",E17=0),"",E17*Setup!D9)
A19: Gain/loss % | E19: =IF(OR(E18="",E16=0),"",(E18-E16)/E16)
A20: Your portfolio minus benchmark (pts) | E20: =IF(OR(J9="",E19=""),"",J9-E19)
A21: Positive = your mix is beating a plain S&P 500 fund. Read it over months, not days.
A23: Next payday buy planner
A24: Ticker | B24: Sleeve | C24: Target | D24: AED | E24: USD | F24: Est. fee (USD) | G24: Fee % of buy
A25: =Setup!B9 -> VOO | B25: =Setup!A9 -> US equity (S&P 500) | C25: =Setup!C9 -> 0.65 | D25: =Setup!$B$4*C25 -> 2600 | E25: =D25/Setup!$B$3 -> 707.9646 | F25: =MAX(Setup!$B$5,Setup!$B$6*E25) -> 1.7699115 | G25: =IF(E25=0,"",F25/E25) -> 0.0025
A26: =Setup!B10 -> SGOV | B26: =Setup!A10 -> Short-term Treasuries / TIPS | C26: =Setup!C10 -> 0.125 | D26: =Setup!$B$4*C26 -> 500 | E26: =D26/Setup!$B$3 -> 136.14704 | F26: =MAX(Setup!$B$5,Setup!$B$6*E26) -> 1 | G26: =IF(E26=0,"",F26/E26) -> 0.007345
A27: =Setup!B11 -> ITA | B27: =Setup!A11 -> Defense / aerospace | C27: =Setup!C11 -> 0.1125 | D27: =Setup!$B$4*C27 -> 450 | E27: =D27/Setup!$B$3 -> 122.53233 | F27: =MAX(Setup!$B$5,Setup!$B$6*E27) -> 1 | G27: =IF(E27=0,"",F27/E27) -> 0.0081611111
A28: =Setup!B12 -> NLR | B28: =Setup!A12 -> Nuclear energy | C28: =Setup!C12 -> 0.1125 | D28: =Setup!$B$4*C28 -> 450 | E28: =D28/Setup!$B$3 -> 122.53233 | F28: =MAX(Setup!$B$5,Setup!$B$6*E28) -> 1 | G28: =IF(E28=0,"",F28/E28) -> 0.0081611111
A29: Total | C29: =SUM(C25:C28) -> 1 | D29: =SUM(D25:D28) -> 4000 | E29: =SUM(E25:E28) -> 1089.1763 | F29: =SUM(F25:F28) -> 4.7699115 | G29: =IF(E29=0,"",F29/E29) -> 0.004379375

Sheet Setup
A1: Setup
A3: AED/USD peg | B3: 3.6725 | C3: Fixed peg used in the plan.
A4: Monthly contribution (AED) | B4: 4000 | C4: From your plan.
A5: Fee minimum per trade (USD) | B5: 1 | C5: Sarwa Trade reported fee: greater of $1 or 0.25%. Verify in the app.
A6: Fee rate | B6: 0.0025 | C6: As above.
A8: Sleeve | B8: Ticker | C8: Target % | D8: Current price (USD) - auto from Weekly Log | E8: Latest log date | F8: Note
A9: US equity (S&P 500) | B9: VOO | C9: 0.65 | D9: =IF(COUNT('Weekly Log'!B$2:B$60)=0,"",INDEX('Weekly Log'!B$2:B$60,COUNT('Weekly Log'!B$2:B$60))) | E9: =IF(COUNT('Weekly Log'!$A$2:$A$60)=0,"",INDEX('Weekly Log'!$A$2:$A$60,COUNT('Weekly Log'!$A$2:$A$60))) -> 46303 | F9: Paper pick. Alternatives: IVV or another S&P 500 ETF. Verify availability and fees on Sarwa.
A10: Short-term Treasuries / TIPS | B10: SGOV | C10: 0.125 | D10: =IF(COUNT('Weekly Log'!C$2:C$60)=0,"",INDEX('Weekly Log'!C$2:C$60,COUNT('Weekly Log'!C$2:C$60))) | E10: =IF(COUNT('Weekly Log'!$A$2:$A$60)=0,"",INDEX('Weekly Log'!$A$2:$A$60,COUNT('Weekly Log'!$A$2:$A$60))) -> 46303 | F10: Paper pick (T-bills). Alternative: a short-term TIPS fund.
A11: Defense / aerospace | B11: ITA | C11: 0.1125 | D11: =IF(COUNT('Weekly Log'!D$2:D$60)=0,"",INDEX('Weekly Log'!D$2:D$60,COUNT('Weekly Log'!D$2:D$60))) | E11: =IF(COUNT('Weekly Log'!$A$2:$A$60)=0,"",INDEX('Weekly Log'!$A$2:$A$60,COUNT('Weekly Log'!$A$2:$A$60))) -> 46303 | F11: Paper pick (sector ETF). Single names can replace it later.
A12: Nuclear energy | B12: NLR | C12: 0.1125 | D12: =IF(COUNT('Weekly Log'!E$2:E$60)=0,"",INDEX('Weekly Log'!E$2:E$60,COUNT('Weekly Log'!E$2:E$60))) | E12: =IF(COUNT('Weekly Log'!$A$2:$A$60)=0,"",INDEX('Weekly Log'!$A$2:$A$60,COUNT('Weekly Log'!$A$2:$A$60))) -> 46303 | F12: Reference only: closed about $102.74 on 2 Oct 2026 (trade-ideas.com). Enter your own price.
A13: Total target | C13: =SUM(C9:C12) -> 1 | D13: =IF(ROUND(C13,4)=1,"OK","Targets must sum to 100%") -> OK
A15: Wildcard sleeve: parked at 0% until you name a pick.

Sheet Ledger
A1: Date | B1: Ticker | C1: Sleeve | D1: AED allocated | E1: USD gross | F1: Fee (USD) | G1: Fill price (USD) | H1: Units | I1: Notes
A2: 46303 | B2: VOO | C2: =IF(B2="","",IFERROR(INDEX(Setup!$A$9:$A$12,MATCH(B2,Setup!$B$9:$B$12,0)),"Ticker not in Setup")) -> US equity (S&P 500) | D2: 2600 | E2: =IF(D2="","",D2/Setup!$B$3) -> 707.9646 | F2: =IF(E2="","",MAX(Setup!$B$5,Setup!$B$6*E2)) -> 1.7699115 | H2: =IF(OR(G2="",E2=""),"",(E2-F2)/G2)
A3: 46303 | B3: SGOV | C3: =IF(B3="","",IFERROR(INDEX(Setup!$A$9:$A$12,MATCH(B3,Setup!$B$9:$B$12,0)),"Ticker not in Setup")) -> Short-term Treasuries / TIPS | D3: 500 | E3: =IF(D3="","",D3/Setup!$B$3) -> 136.14704 | F3: =IF(E3="","",MAX(Setup!$B$5,Setup!$B$6*E3)) -> 1 | H3: =IF(OR(G3="",E3=""),"",(E3-F3)/G3)
A4: 46303 | B4: ITA | C4: =IF(B4="","",IFERROR(INDEX(Setup!$A$9:$A$12,MATCH(B4,Setup!$B$9:$B$12,0)),"Ticker not in Setup")) -> Defense / aerospace | D4: 450 | E4: =IF(D4="","",D4/Setup!$B$3) -> 122.53233 | F4: =IF(E4="","",MAX(Setup!$B$5,Setup!$B$6*E4)) -> 1 | H4: =IF(OR(G4="",E4=""),"",(E4-F4)/G4)
A5: 46303 | B5: NLR | C5: =IF(B5="","",IFERROR(INDEX(Setup!$A$9:$A$12,MATCH(B5,Setup!$B$9:$B$12,0)),"Ticker not in Setup")) -> Nuclear energy | D5: 450 | E5: =IF(D5="","",D5/Setup!$B$3) -> 122.53233 | F5: =IF(E5="","",MAX(Setup!$B$5,Setup!$B$6*E5)) -> 1 | H5: =IF(OR(G5="",E5=""),"",(E5-F5)/G5)
C6: =IF(B6="","",IFERROR(INDEX(Setup!$A$9:$A$12,MATCH(B6,Setup!$B$9:$B$12,0)),"Ticker not in Setup")) | E6: =IF(D6="","",D6/Setup!$B$3) | F6: =IF(E6="","",MAX(Setup!$B$5,Setup!$B$6*E6)) | H6: =IF(OR(G6="",E6=""),"",(E6-F6)/G6)
C7: =IF(B7="","",IFERROR(INDEX(Setup!$A$9:$A$12,MATCH(B7,Setup!$B$9:$B$12,0)),"Ticker not in Setup")) | E7: =IF(D7="","",D7/Setup!$B$3) | F7: =IF(E7="","",MAX(Setup!$B$5,Setup!$B$6*E7)) | H7: =IF(OR(G7="",E7=""),"",(E7-F7)/G7)
C8: =IF(B8="","",IFERROR(INDEX(Setup!$A$9:$A$12,MATCH(B8,Setup!$B$9:$B$12,0)),"Ticker not in Setup")) | E8: =IF(D8="","",D8/Setup!$B$3) | F8: =IF(E8="","",MAX(Setup!$B$5,Setup!$B$6*E8)) | H8: =IF(OR(G8="",E8=""),"",(E8-F8)/G8)
C9: =IF(B9="","",IFERROR(INDEX(Setup!$A$9:$A$12,MATCH(B9,Setup!$B$9:$B$12,0)),"Ticker not in Setup")) | E9: =IF(D9="","",D9/Setup!$B$3) | F9: =IF(E9="","",MAX(Setup!$B$5,Setup!$B$6*E9)) | H9: =IF(OR(G9="",E9=""),"",(E9-F9)/G9)
C10: =IF(B10="","",IFERROR(INDEX(Setup!$A$9:$A$12,MATCH(B10,Setup!$B$9:$B$12,0)),"Ticker not in Setup")) | E10: =IF(D10="","",D10/Setup!$B$3) | F10: =IF(E10="","",MAX(Setup!$B$5,Setup!$B$6*E10)) | H10: =IF(OR(G10="",E10=""),"",(E10-F10)/G10)
C11: =IF(B11="","",IFERROR(INDEX(Setup!$A$9:$A$12,MATCH(B11,Setup!$B$9:$B$12,0)),"Ticker not in Setup")) | E11: =IF(D11="","",D11/Setup!$B$3) | F11: =IF(E11="","",MAX(Setup!$B$5,Setup!$B$6*E11)) | H11: =IF(OR(G11="",E11=""),"",(E11-F11)/G11)
C12: =IF(B12="","",IFERROR(INDEX(Setup!$A$9:$A$12,MATCH(B12,Setup!$B$9:$B$12,0)),"Ticker not in Setup")) | E12: =IF(D12="","",D12/Setup!$B$3) | F12: =IF(E12="","",MAX(Setup!$B$5,Setup!$B$6*E12)) | H12: =IF(OR(G12="",E12=""),"",(E12-F12)/G12)
C13: =IF(B13="","",IFERROR(INDEX(Setup!$A$9:$A$12,MATCH(B13,Setup!$B$9:$B$12,0)),"Ticker not in Setup")) | E13: =IF(D13="","",D13/Setup!$B$3) | F13: =IF(E13="","",MAX(Setup!$B$5,Setup!$B$6*E13)) | H13: =IF(OR(G13="",E13=""),"",(E13-F13)/G13)
C14: =IF(B14="","",IFERROR(INDEX(Setup!$A$9:$A$12,MATCH(B14,Setup!$B$9:$B$12,0)),"Ticker not in Setup")) | E14: =IF(D14="","",D14/Setup!$B$3) | F14: =IF(E14="","",MAX(Setup!$B$5,Setup!$B$6*E14)) | H14: =IF(OR(G14="",E14=""),"",(E14-F14)/G14)
C15: =IF(B15="","",IFERROR(INDEX(Setup!$A$9:$A$12,MATCH(B15,Setup!$B$9:$B$12,0)),"Ticker not in Setup")) | E15: =IF(D15="","",D15/Setup!$B$3) | F15: =IF(E15="","",MAX(Setup!$B$5,Setup!$B$6*E15)) | H15: =IF(OR(G15="",E15=""),"",(E15-F15)/G15)
C16: =IF(B16="","",IFERROR(INDEX(Setup!$A$9:$A$12,MATCH(B16,Setup!$B$9:$B$12,0)),"Ticker not in Setup")) | E16: =IF(D16="","",D16/Setup!$B$3) | F16: =IF(E16="","",MAX(Setup!$B$5,Setup!$B$6*E16)) | H16: =IF(OR(G16="",E16=""),"",(E16-F16)/G16)
C17: =IF(B17="","",IFERROR(INDEX(Setup!$A$9:$A$12,MATCH(B17,Setup!$B$9:$B$12,0)),"Ticker not in Setup")) | E17: =IF(D17="","",D17/Setup!$B$3) | F17: =IF(E17="","",MAX(Setup!$B$5,Setup!$B$6*E17)) | H17: =IF(OR(G17="",E17=""),"",(E17-F17)/G17)
... C200: =IF(B200="","",IFERROR(INDEX(Setup!$A$9:$A$12,MATCH(B200,Setup!$B$9:$B$12,0)),"Ticker not in Setup")) | E200: =IF(D200="","",D200/Setup!$B$3) | F200: =IF(E200="","",MAX(Setup!$B$5,Setup!$B$6*E200)) | H200: =IF(OR(G200="",E200=""),"",(E200-F200)/G200)

Sheet Contributions
A1: Date | B1: AED contributed | C1: VOO price that day (USD) | D1: USD gross | E1: Fee (USD) | F1: Benchmark units (VOO only) | H1: Enter the VOO fill price for each contribution date. The benchmark assumes the whole contribution buys VOO in one trade.
A2: 46303 | B2: 4000 | D2: =IF(B2="","",B2/Setup!$B$3) -> 1089.1763 | E2: =IF(D2="","",MAX(Setup!$B$5,Setup!$B$6*D2)) -> 2.7229408 | F2: =IF(OR(C2="",D2=""),"",(D2-E2)/C2)
D3: =IF(B3="","",B3/Setup!$B$3) | E3: =IF(D3="","",MAX(Setup!$B$5,Setup!$B$6*D3)) | F3: =IF(OR(C3="",D3=""),"",(D3-E3)/C3)
D4: =IF(B4="","",B4/Setup!$B$3) | E4: =IF(D4="","",MAX(Setup!$B$5,Setup!$B$6*D4)) | F4: =IF(OR(C4="",D4=""),"",(D4-E4)/C4)
D5: =IF(B5="","",B5/Setup!$B$3) | E5: =IF(D5="","",MAX(Setup!$B$5,Setup!$B$6*D5)) | F5: =IF(OR(C5="",D5=""),"",(D5-E5)/C5)
D6: =IF(B6="","",B6/Setup!$B$3) | E6: =IF(D6="","",MAX(Setup!$B$5,Setup!$B$6*D6)) | F6: =IF(OR(C6="",D6=""),"",(D6-E6)/C6)
D7: =IF(B7="","",B7/Setup!$B$3) | E7: =IF(D7="","",MAX(Setup!$B$5,Setup!$B$6*D7)) | F7: =IF(OR(C7="",D7=""),"",(D7-E7)/C7)
D8: =IF(B8="","",B8/Setup!$B$3) | E8: =IF(D8="","",MAX(Setup!$B$5,Setup!$B$6*D8)) | F8: =IF(OR(C8="",D8=""),"",(D8-E8)/C8)
D9: =IF(B9="","",B9/Setup!$B$3) | E9: =IF(D9="","",MAX(Setup!$B$5,Setup!$B$6*D9)) | F9: =IF(OR(C9="",D9=""),"",(D9-E9)/C9)
D10: =IF(B10="","",B10/Setup!$B$3) | E10: =IF(D10="","",MAX(Setup!$B$5,Setup!$B$6*D10)) | F10: =IF(OR(C10="",D10=""),"",(D10-E10)/C10)
D11: =IF(B11="","",B11/Setup!$B$3) | E11: =IF(D11="","",MAX(Setup!$B$5,Setup!$B$6*D11)) | F11: =IF(OR(C11="",D11=""),"",(D11-E11)/C11)
D12: =IF(B12="","",B12/Setup!$B$3) | E12: =IF(D12="","",MAX(Setup!$B$5,Setup!$B$6*D12)) | F12: =IF(OR(C12="",D12=""),"",(D12-E12)/C12)
D13: =IF(B13="","",B13/Setup!$B$3) | E13: =IF(D13="","",MAX(Setup!$B$5,Setup!$B$6*D13)) | F13: =IF(OR(C13="",D13=""),"",(D13-E13)/C13)
D14: =IF(B14="","",B14/Setup!$B$3) | E14: =IF(D14="","",MAX(Setup!$B$5,Setup!$B$6*D14)) | F14: =IF(OR(C14="",D14=""),"",(D14-E14)/C14)
... D61: =IF(B61="","",B61/Setup!$B$3) | E61: =IF(D61="","",MAX(Setup!$B$5,Setup!$B$6*D61)) | F61: =IF(OR(C61="",D61=""),"",(D61-E61)/C61)

Sheet Weekly Log
A1: Date (week) | B1: VOO | C1: SGOV | D1: ITA | E1: NLR | F1: CEG | G1: CCJ | I1: VOO idx | J1: SGOV idx | K1: ITA idx | L1: NLR idx | M1: CEG idx | N1: CCJ idx
A2: 46303 | I2: =IF(OR(B2="",B$2=""),"",B2/B$2*100) | J2: =IF(OR(C2="",C$2=""),"",C2/C$2*100) | K2: =IF(OR(D2="",D$2=""),"",D2/D$2*100) | L2: =IF(OR(E2="",E$2=""),"",E2/E$2*100) | M2: =IF(OR(F2="",F$2=""),"",F2/F$2*100) | N2: =IF(OR(G2="",G$2=""),"",G2/G$2*100)
I3: =IF(OR(B3="",B$2=""),"",B3/B$2*100) | J3: =IF(OR(C3="",C$2=""),"",C3/C$2*100) | K3: =IF(OR(D3="",D$2=""),"",D3/D$2*100) | L3: =IF(OR(E3="",E$2=""),"",E3/E$2*100) | M3: =IF(OR(F3="",F$2=""),"",F3/F$2*100) | N3: =IF(OR(G3="",G$2=""),"",G3/G$2*100)
I4: =IF(OR(B4="",B$2=""),"",B4/B$2*100) | J4: =IF(OR(C4="",C$2=""),"",C4/C$2*100) | K4: =IF(OR(D4="",D$2=""),"",D4/D$2*100) | L4: =IF(OR(E4="",E$2=""),"",E4/E$2*100) | M4: =IF(OR(F4="",F$2=""),"",F4/F$2*100) | N4: =IF(OR(G4="",G$2=""),"",G4/G$2*100)
I5: =IF(OR(B5="",B$2=""),"",B5/B$2*100) | J5: =IF(OR(C5="",C$2=""),"",C5/C$2*100) | K5: =IF(OR(D5="",D$2=""),"",D5/D$2*100) | L5: =IF(OR(E5="",E$2=""),"",E5/E$2*100) | M5: =IF(OR(F5="",F$2=""),"",F5/F$2*100) | N5: =IF(OR(G5="",G$2=""),"",G5/G$2*100)
I6: =IF(OR(B6="",B$2=""),"",B6/B$2*100) | J6: =IF(OR(C6="",C$2=""),"",C6/C$2*100) | K6: =IF(OR(D6="",D$2=""),"",D6/D$2*100) | L6: =IF(OR(E6="",E$2=""),"",E6/E$2*100) | M6: =IF(OR(F6="",F$2=""),"",F6/F$2*100) | N6: =IF(OR(G6="",G$2=""),"",G6/G$2*100)
I7: =IF(OR(B7="",B$2=""),"",B7/B$2*100) | J7: =IF(OR(C7="",C$2=""),"",C7/C$2*100) | K7: =IF(OR(D7="",D$2=""),"",D7/D$2*100) | L7: =IF(OR(E7="",E$2=""),"",E7/E$2*100) | M7: =IF(OR(F7="",F$2=""),"",F7/F$2*100) | N7: =IF(OR(G7="",G$2=""),"",G7/G$2*100)
I8: =IF(OR(B8="",B$2=""),"",B8/B$2*100) | J8: =IF(OR(C8="",C$2=""),"",C8/C$2*100) | K8: =IF(OR(D8="",D$2=""),"",D8/D$2*100) | L8: =IF(OR(E8="",E$2=""),"",E8/E$2*100) | M8: =IF(OR(F8="",F$2=""),"",F8/F$2*100) | N8: =IF(OR(G8="",G$2=""),"",G8/G$2*100)
I9: =IF(OR(B9="",B$2=""),"",B9/B$2*100) | J9: =IF(OR(C9="",C$2=""),"",C9/C$2*100) | K9: =IF(OR(D9="",D$2=""),"",D9/D$2*100) | L9: =IF(OR(E9="",E$2=""),"",E9/E$2*100) | M9: =IF(OR(F9="",F$2=""),"",F9/F$2*100) | N9: =IF(OR(G9="",G$2=""),"",G9/G$2*100)
I10: =IF(OR(B10="",B$2=""),"",B10/B$2*100) | J10: =IF(OR(C10="",C$2=""),"",C10/C$2*100) | K10: =IF(OR(D10="",D$2=""),"",D10/D$2*100) | L10: =IF(OR(E10="",E$2=""),"",E10/E$2*100) | M10: =IF(OR(F10="",F$2=""),"",F10/F$2*100) | N10: =IF(OR(G10="",G$2=""),"",G10/G$2*100)
I11: =IF(OR(B11="",B$2=""),"",B11/B$2*100) | J11: =IF(OR(C11="",C$2=""),"",C11/C$2*100) | K11: =IF(OR(D11="",D$2=""),"",D11/D$2*100) | L11: =IF(OR(E11="",E$2=""),"",E11/E$2*100) | M11: =IF(OR(F11="",F$2=""),"",F11/F$2*100) | N11: =IF(OR(G11="",G$2=""),"",G11/G$2*100)
I12: =IF(OR(B12="",B$2=""),"",B12/B$2*100) | J12: =IF(OR(C12="",C$2=""),"",C12/C$2*100) | K12: =IF(OR(D12="",D$2=""),"",D12/D$2*100) | L12: =IF(OR(E12="",E$2=""),"",E12/E$2*100) | M12: =IF(OR(F12="",F$2=""),"",F12/F$2*100) | N12: =IF(OR(G12="",G$2=""),"",G12/G$2*100)
I13: =IF(OR(B13="",B$2=""),"",B13/B$2*100) | J13: =IF(OR(C13="",C$2=""),"",C13/C$2*100) | K13: =IF(OR(D13="",D$2=""),"",D13/D$2*100) | L13: =IF(OR(E13="",E$2=""),"",E13/E$2*100) | M13: =IF(OR(F13="",F$2=""),"",F13/F$2*100) | N13: =IF(OR(G13="",G$2=""),"",G13/G$2*100)
I14: =IF(OR(B14="",B$2=""),"",B14/B$2*100) | J14: =IF(OR(C14="",C$2=""),"",C14/C$2*100) | K14: =IF(OR(D14="",D$2=""),"",D14/D$2*100) | L14: =IF(OR(E14="",E$2=""),"",E14/E$2*100) | M14: =IF(OR(F14="",F$2=""),"",F14/F$2*100) | N14: =IF(OR(G14="",G$2=""),"",G14/G$2*100)
... I60: =IF(OR(B60="",B$2=""),"",B60/B$2*100) | J60: =IF(OR(C60="",C$2=""),"",C60/C$2*100) | K60: =IF(OR(D60="",D$2=""),"",D60/D$2*100) | L60: =IF(OR(E60="",E$2=""),"",E60/E$2*100) | M60: =IF(OR(F60="",F$2=""),"",F60/F$2*100) | N60: =IF(OR(G60="",G$2=""),"",G60/G$2*100)
A62: One row per week, same weekday (for example Thursday close), no gaps. Row 2 is the baseline: the price on your first paper-investment date (8 Oct 2026).
A63: Idx columns rebase each price to 100 at the baseline so different-priced funds can be compared. CEG and CCJ are comparisons only: no money is assigned to them.
